yta_audio_sounds/__init__.py
yta_audio_sounds/downloader.py
yta_audio_sounds/generation.py
yta_audio_sounds/resources/__init__.py
yta_audio_sounds/resources/drive_urls.py
yta_audio_sounds-0.0.2.dist-info/LICENSE
yta_audio_sounds-0.0.2.dist-info/METADATA
yta_audio_sounds-0.0.2.dist-info/WHEEL
yta_audio_sounds-0.0.2.dist-info/RECORD
